{
  "hash": "e384ce68",
  "configHash": "23268b6a",
  "lockfileHash": "632d9151",
  "browserHash": "9db50640",
  "optimized": {
    "lucide-react": {
      "src": "../../node_modules/lucide-react/dist/esm/lucide-react.mjs",
      "file": "lucide-react.js",
      "fileHash": "9daaa683",
      "needsInterop": false
    },
    "react-dom": {
      "src": "../../node_modules/react-dom/index.js",
      "file": "react-dom.js",
      "fileHash": "fff23666",
      "needsInterop": true
    },
    "react-dom/client": {
      "src": "../../node_modules/react-dom/client.js",
      "file": "react-dom_client.js",
      "fileHash": "616d283f",
      "needsInterop": true
    },
    "react-icons/fa": {
      "src": "../../node_modules/react-icons/fa/index.mjs",
      "file": "react-icons_fa.js",
      "fileHash": "c4f6a76e",
      "needsInterop": false
    },
    "react-icons/gr": {
      "src": "../../node_modules/react-icons/gr/index.mjs",
      "file": "react-icons_gr.js",
      "fileHash": "f89eb50c",
      "needsInterop": false
    },
    "react": {
      "src": "../../node_modules/react/index.js",
      "file": "react.js",
      "fileHash": "e759b558",
      "needsInterop": true
    },
    "react/jsx-dev-runtime": {
      "src": "../../node_modules/react/jsx-dev-runtime.js",
      "file": "react_jsx-dev-runtime.js",
      "fileHash": "1bc89d12",
      "needsInterop": true
    },
    "react/jsx-runtime": {
      "src": "../../node_modules/react/jsx-runtime.js",
      "file": "react_jsx-runtime.js",
      "fileHash": "1b31a1c2",
      "needsInterop": true
    }
  },
  "chunks": {
    "iconBase-DK0L-Xqu": {
      "file": "iconBase-DK0L-Xqu.js",
      "isDynamicEntry": false
    },
    "react-BDWiK9rz": {
      "file": "react-BDWiK9rz.js",
      "isDynamicEntry": false
    }
  }
}